LICENSE
README.md
setup.py
lamassu/__init__.py
lamassu.egg-info/PKG-INFO
lamassu.egg-info/SOURCES.txt
lamassu.egg-info/dependency_links.txt
lamassu.egg-info/not-zip-safe
lamassu.egg-info/top_level.txt
lamassu/rnn/__init__.py
lamassu/rnn/example.py
lamassu/rnn/rnn.py
lamassu/speech/__init__.py
lamassu/speech/sampling.py