Metadata-Version: 2.1
Name: lamassu
Version: 0.0.13
Summary: Empowering individual to agnostically run machine learning algorithms to produce ad-hoc AI features
Home-page: https://github.com/QubitPi/lamassu
Author: Jiaqi liu
Author-email: jack20220723@gmail.com
License: Apache-2.0
Requires-Python: >=3.10
License-File: LICENSE
